nusterdb/__init__.py
nusterdb/cache_backend.py
nusterdb/client.py
nusterdb/config.py
nusterdb/core.py
nusterdb/exceptions.py
nusterdb/memory_backend.py
nusterdb/persistent_backend.py
nusterdb/py.typed
nusterdb/utils.py
nusterdb-2.1.3.dist-info/licenses/LICENSE
nusterdb-2.1.3.dist-info/METADATA
nusterdb-2.1.3.dist-info/WHEEL
nusterdb-2.1.3.dist-info/entry_points.txt
nusterdb-2.1.3.dist-info/top_level.txt
nusterdb-2.1.3.dist-info/RECORD
