Metadata-Version: 2.4
Name: nusterdb
Version: 2.1.3
Summary: High-performance, government-grade vector database with advanced indexing algorithms
Home-page: https://github.com/NusterAI/nusterdb
Author: NusterAI Team
Author-email: NusterAI Team <info@nusterai.com>
Maintainer-email: NusterAI Team <info@nusterai.com>
License-Expression: MIT
Project-URL: Homepage, https://github.com/NusterAI/nusterdb
Project-URL: Documentation, https://docs.nusterai.com/nusterdb
Project-URL: Repository, https://github.com/NusterAI/nusterdb
Project-URL: Bug Tracker, https://github.com/NusterAI/nusterdb/issues
Project-URL: Changelog, https://github.com/NusterAI/nusterdb/blob/main/CHANGELOG.md
Keywords: vector database,similarity search,machine learning,AI,government-grade,security,FIPS,quantum-resistant
Classifier: Development Status :: 5 - Production/Stable
Classifier: Intended Audience :: Developers
Classifier: Intended Audience :: Science/Research
Classifier: Topic :: Database
Classifier: Topic :: Scientific/Engineering :: Artificial Intelligence
Classifier: Programming Language :: Python :: 3
Classifier: Programming Language :: Python :: 3.8
Classifier: Programming Language :: Python :: 3.9
Classifier: Programming Language :: Python :: 3.10
Classifier: Programming Language :: Python :: 3.11
Classifier: Programming Language :: Python :: 3.12
Classifier: Operating System :: OS Independent
Classifier: Environment :: GPU :: NVIDIA CUDA
Classifier: Environment :: MacOS X
Classifier: Environment :: Win32 (MS Windows)
Requires-Python: >=3.8
License-File: LICENSE
Requires-Dist: numpy>=1.20.0
Requires-Dist: requests>=2.25.0
Requires-Dist: typing-extensions>=4.0.0
Provides-Extra: dev
Requires-Dist: pytest>=6.0; extra == "dev"
Requires-Dist: pytest-benchmark>=3.4.0; extra == "dev"
Requires-Dist: black>=21.0.0; extra == "dev"
Requires-Dist: mypy>=0.900; extra == "dev"
Requires-Dist: pre-commit>=2.15.0; extra == "dev"
Requires-Dist: build>=0.8.0; extra == "dev"
Requires-Dist: twine>=4.0.0; extra == "dev"
Provides-Extra: benchmark
Requires-Dist: faiss-cpu>=1.7.0; extra == "benchmark"
Requires-Dist: matplotlib>=3.5.0; extra == "benchmark"
Requires-Dist: pandas>=1.5.0; extra == "benchmark"
Requires-Dist: psutil>=5.8.0; extra == "benchmark"
Provides-Extra: server
Requires-Dist: uvicorn>=0.15.0; extra == "server"
Requires-Dist: fastapi>=0.68.0; extra == "server"
Provides-Extra: security
Requires-Dist: cryptography>=3.4.8; extra == "security"
Requires-Dist: pycryptodome>=3.15.0; extra == "security"
Dynamic: author
Dynamic: home-page
Dynamic: license-file
Dynamic: requires-python
